queues_master_new/__init__.py
queues_master_new/queues.py
queues_master_new-1.0.4.dist-info/METADATA
queues_master_new-1.0.4.dist-info/WHEEL
queues_master_new-1.0.4.dist-info/top_level.txt
queues_master_new-1.0.4.dist-info/RECORD
