Metadata-Version: 2.1
Name: queues-master-new
Version: 1.0.4
Author: itskekoff
Requires-Dist: requests
